pydistance/__init__.py
pydistance-0.0.2.data/scripts/pyd
pydistance-0.0.2.dist-info/METADATA
pydistance-0.0.2.dist-info/RECORD
pydistance-0.0.2.dist-info/WHEEL
pydistance-0.0.2.dist-info/top_level.txt
