Metadata-Version: 2.1
Name: pydistance
Version: 0.0.2
Summary: Package for plotting the closest point for a given set of coordinates
Home-page: https://github.com/dang3r/pydistance
Author: Daniel Cardoza
Author-email: dan@danielcardoza.com
License: MIT
Platform: UNKNOWN
Requires-Python: >=3.4.0
Requires-Dist: geopy
Requires-Dist: pytz
Requires-Dist: gmplot
Requires-Dist: click
Requires-Dist: googlemaps
